spec_line/__init__.py
spec_line/cli.py
spec_line/scaffold.py
specline-0.1.0.dist-info/METADATA
specline-0.1.0.dist-info/WHEEL
specline-0.1.0.dist-info/entry_points.txt
specline-0.1.0.dist-info/top_level.txt
specline-0.1.0.dist-info/RECORD
