Metadata-Version: 2.4
Name: specline
Version: 0.1.0
Summary: SpecLine CLI for managing specline/ OpenSpec workflows
Requires-Python: >=3.10
Provides-Extra: test
Requires-Dist: pytest>=8.0; extra == "test"
